manage/__init__.py
manage/__main__.py
manage/errors.py
manage/install.py
manage/rest.py
manage/service.py
manage/define/portal.json
manage/define/rest.json
body_manage-1.0.7.dist-info/METADATA
body_manage-1.0.7.dist-info/WHEEL
body_manage-1.0.7.dist-info/entry_points.txt
body_manage-1.0.7.dist-info/licenses/LICENSE
body_manage-1.0.7.dist-info/RECORD
