Metadata-Version: 2.4
Name: body_manage
Version: 1.0.7
Summary: Manage contains a service to manage the services themselves
Project-URL: Documentation, https://github.com/ouroboroscoding/body-manage
Project-URL: Source, https://github.com/ouroboroscoding/body-manage
Project-URL: Tracker, https://github.com/ouroboroscoding/body-manage/issues
Author-email: "Chris Nasr - Ouroboros Coding Inc." <chris@ouroboroscoding.com>
Maintainer-email: "Chris Nasr - Ouroboros Coding Inc." <chris@ouroboroscoding.com>
License-File: LICENSE
Requires-Python: >=3.10
Requires-Dist: arrow<1.4,>=1.3.0
Requires-Dist: brain2-oc<2.5,>=2.3.2
Requires-Dist: config-oc<1.2,>=1.1.0
Requires-Dist: define-oc<1.1,>=1.0.5
Requires-Dist: email-smtp<1.1,>=1.0.1
Requires-Dist: jsonb<1.1,>=1.0.0
